gy_redis/__init__.py
gy_redis/handler.py
gy_redis/manager.py
gy_redis-0.1.9.dist-info/LICENSE
gy_redis-0.1.9.dist-info/METADATA
gy_redis-0.1.9.dist-info/WHEEL
gy_redis-0.1.9.dist-info/dependency_links.txt
gy_redis-0.1.9.dist-info/top_level.txt
gy_redis-0.1.9.dist-info/RECORD
